_balder/__init__.py
_balder/_version.py
_balder/balder_plugin.py
_balder/balder_session.py
_balder/balder_settings.py
_balder/collector.py
_balder/connection.py
_balder/connection_metadata.py
_balder/decorator_connect.py
_balder/decorator_covered_by.py
_balder/decorator_fixture.py
_balder/decorator_for_vdevice.py
_balder/decorator_gateway.py
_balder/decorator_insert_into_tree.py
_balder/decorator_parametrize.py
_balder/decorator_parametrize_by_feature.py
_balder/device.py
_balder/exceptions.py
_balder/exit_code.py
_balder/feature.py
_balder/feature_replacement_mapping.py
_balder/feature_vdevice_mapping.py
_balder/fixture_definition_scope.py
_balder/fixture_execution_level.py
_balder/fixture_manager.py
_balder/fixture_metadata.py
_balder/node_gateway.py
_balder/parametrization.py
_balder/plugin_manager.py
_balder/previous_executor_mark.py
_balder/routing_path.py
_balder/scenario.py
_balder/setup.py
_balder/solver.py
_balder/testresult.py
_balder/unmapped_vdevice.py
_balder/vdevice.py
_balder/cnnrelations/__init__.py
_balder/cnnrelations/and_connection_relation.py
_balder/cnnrelations/base_connection_relation.py
_balder/cnnrelations/or_connection_relation.py
_balder/console/__init__.py
_balder/console/balder.py
_balder/controllers/__init__.py
_balder/controllers/base_device_controller.py
_balder/controllers/controller.py
_balder/controllers/device_controller.py
_balder/controllers/feature_controller.py
_balder/controllers/normal_scenario_setup_controller.py
_balder/controllers/scenario_controller.py
_balder/controllers/setup_controller.py
_balder/controllers/vdevice_controller.py
_balder/executor/__init__.py
_balder/executor/basic_executable_executor.py
_balder/executor/basic_executor.py
_balder/executor/executor_tree.py
_balder/executor/parametrized_testcase_executor.py
_balder/executor/scenario_executor.py
_balder/executor/setup_executor.py
_balder/executor/testcase_executor.py
_balder/executor/unresolved_parametrized_testcase_executor.py
baldertest-0.1.1.dist-info/licenses/LICENSE
baldertest-0.1.1.dist-info/METADATA
baldertest-0.1.1.dist-info/WHEEL
baldertest-0.1.1.dist-info/entry_points.txt
baldertest-0.1.1.dist-info/top_level.txt
baldertest-0.1.1.dist-info/RECORD
