Metadata-Version: 2.4
Name: baldertest
Version: 0.1.1
Summary: balder: reusable scenario based test framework
Home-page: https://docs.balder.dev
Author: Max Stahlschmidt and others
License: MIT
Project-URL: Source, https://github.com/balder-dev/balder
Project-URL: Tracker, https://github.com/balder-dev/balder/issues
Keywords: test,systemtest,reusable,scenario
Platform: unix
Platform: linux
Platform: osx
Platform: cygwin
Platform: win32
Classifier: License :: OSI Approved :: MIT License
Classifier: Operating System :: MacOS :: MacOS X
Classifier: Operating System :: Microsoft :: Windows
Classifier: Operating System :: POSIX
Classifier: Intended Audience :: Developers
Classifier: Programming Language :: Python :: 3
Classifier: Programming Language :: Python :: 3 :: Only
Classifier: Programming Language :: Python :: 3.9
Classifier: Programming Language :: Python :: 3.10
Classifier: Programming Language :: Python :: 3.11
Classifier: Programming Language :: Python :: 3.12
Classifier: Programming Language :: Python :: 3.13
Classifier: Programming Language :: Python :: 3.14
Classifier: Topic :: Software Development :: Libraries
Classifier: Topic :: Software Development :: Testing
Classifier: Topic :: Utilities
Requires-Python: >=3.9
License-File: LICENSE
Dynamic: license-file
